{
    "entry_id":  101,
    "chapter_idx":  10,
    "chapter_title":  "Student debriefing",
    "chapter_url":  "https://www2.education.vic.gov.au/pal/structured-workplace-learning/guidance/student-debriefing-after-placement",
    "snippet":  "Schools must provide students with the opportunity to debrief after their placement. This will involve reflecting on: Structured workplace learning coordinators and other relevant staff are encouraged to collect written or verbal feedback from employers and parents/carers. These comments provide insight into the value of the placement for the student from the perspective of parents/carers and employers. For schools using the WBL App for structured workplace learning arrangements, the App will automatically send evaluation survey forms to students and employers after a placement ends. Structured workplace learning coordinators and other relevant staff should encourage students to share their experience with other students. At the conclusion of the placement, students are encouraged to write a letter of appreciation to their employer and/or supervisor. Reviewed 20 April 2026",
    "fetched_at":  "2026-04-26T14:25:01.8780930+10:00"
}
