{
    "entry_id":  106.6,
    "chapter_idx":  1,
    "chapter_title":  "Application process for bus accreditation",
    "chapter_url":  "https://www2.education.vic.gov.au/pal/buses-owned-hired-chartered-by-school/guidance/application-process-bus-accreditation",
    "snippet":  "Schools seeking to operate a bus service must by accredited by Safe Transport Victoria. Schools can obtain accreditation by completing the following application process. Schools must download and complete the Application for bus operator accreditation form (PDF) External Link . Note: The school council is the accredited operator and the principal is the relevant person and responsible person. An example of a completed application form (DOCX) External Link , excluding the supporting documents, is provided on the Resources tab. Schools must gather completed copies of the following documents comprising the MIS (refer to the Management information system chapter for guidance on developing an MIS):",
    "fetched_at":  "2026-04-26T19:13:41.9383753+10:00"
}
