{
    "entry_id":  107.1,
    "chapter_idx":  16,
    "chapter_title":  "Conveyance allowance rates",
    "chapter_url":  "https://www2.education.vic.gov.au/pal/conveyance-allowance/guidance/conveyance-allowance-rates",
    "snippet":  "Fares set by TV each year External Link Training for school staff Guidance chapter on the SCAS training and support available ... Public transport accessibility measures Guidance chapter setting out how the Department determines h... Guidance chapter setting out the annual conveyance allowance rates for each type of transport service Reviewed 02 February 2026",
    "fetched_at":  "2026-04-26T19:18:07.3382391+10:00"
}
