{
    "entry_id":  107.7,
    "chapter_idx":  8,
    "chapter_title":  "Special School Transport Administration (Reference 25)",
    "chapter_url":  "https://www2.education.vic.gov.au/pal/student-resource-package-srp-equity-funding-student-based-funding/guidance/8-special-school",
    "snippet":  "A Special School Transport Administration allocation is used to manage transport arrangements in consultation with bus contractors and parents. *Including primary, secondary and primary/secondary combined schools with a defined special school campus. Funding is calculated for each of the 4 school terms. Funding is allocated through cash funding. Funding is calculated based on enrolment ranges provided in the rates section below. For example, a school with 27 enrolments would fall into the 26 to 50 enrolment range.",
    "fetched_at":  "2026-04-26T19:22:07.3474534+10:00"
}
