{
    "entry_id":  107.2,
    "chapter_idx":  3,
    "chapter_title":  "3. Certificates of currency",
    "chapter_url":  "https://www2.education.vic.gov.au/pal/insurance/guidance/3-certificates-currency",
    "snippet":  "Occasionally schools will be asked to supply proof that the school is adequately covered by the department through insurance. This is provided by way of a Certificate of Currency (also known as a Confirmation of Cover). It is a summary of the cover provided. Schools may be asked to supply proof of the following covers: These certificates, and copies of VMIA policies, are available in the Resources tab . Reviewed 18 July 2022",
    "fetched_at":  "2026-04-26T19:19:44.0109286+10:00"
}
