{
    "entry_id":  136.7,
    "chapter_idx":  3,
    "chapter_title":  "3 Developing an Individual Education Plan",
    "chapter_url":  "https://www2.education.vic.gov.au/pal/supporting-students-out-home-care/guidance/3-developing-individual-education-plan",
    "snippet":  "The Student Support Group (SSG) develops the Individual Education Plan (IEP). The purpose of an IEP is to describe a set of strategies to address the particular educational needs of the child or young person in out-of-home care. Developing an IEP is an opportunity to recognise and discuss social and behavioural difficulties and concerns a child may have. It is useful to be aware of the Department of Health and Human Services Looking After Children Framework External Link for context, when developing an IEP. The Department has developed guidance and resources to support the development of IEPS. Refer to the Individual Education Plans Policy for further information.",
    "fetched_at":  "2026-04-26T19:11:44.6113236+10:00"
}
