{
    "entry_id":  15,
    "chapter_idx":  2,
    "chapter_title":  "Education support class",
    "chapter_url":  "https://www2.education.vic.gov.au/pal/attendance-and-working-hours-teaching-service/policy-and-guidelines",
    "snippet":  "The ordinary hours of attendance for a full time education support class employee will be for a minimum of 7.6 hours daily between 7:00am and 6:00pm from Monday to Friday unless otherwise agreed. The principal and the employee may agree on an arrangement of ordinary hours of attendance, including, but not limited to: The principal and employee may agree to vary these arrangements at any time. An education support class employee cannot be required to work more than 5 hours without a lunch break of a minimum duration of 30 minutes. The lunch break is unpaid and free from assigned duties between the hours 11:30am to 2:30pm unless otherwise agreed between the principal and employee as set out above.",
    "fetched_at":  "2026-04-26T13:33:48.0449365+10:00"
}
