{
    "entry_id":  86,
    "chapter_idx":  12,
    "chapter_title":  "First aid",
    "chapter_url":  "https://www2.education.vic.gov.au/pal/excursions/guidance/first-aid",
    "snippet":  "Excursion staff must have first aid and emergency response knowledge appropriate to the excursion location, the students involved and the activities undertaken by each group of students. Staff must also have a first aid kit appropriate to the excursion location, the activities undertaken and the specific needs of participating students with health or medical conditions. Staff must also carefully document student first aid incidents and outcomes on eduSafe Plus or the school’s preferred third party platform. The extent of the first aid training required by staff will be determined by: For excursions involving adventure activities or locations without readily accessible medical support, at least one member of staff responsible for each group of students must hold, as a minimum, a current first aid qualification and a current cardiopulmonary resuscitation (CPR) qualification. Under the Work Health and Safety Act 2010 and the Code of Practice from Safe Work Australia External Link , all first aiders should hold nationally recognised Statement/s of Attainment issued by a Registered Training Organisation (RTO) for the relevant nationally endorsed unit/s of competency.",
    "fetched_at":  "2026-04-26T13:20:00.7917309+10:00"
}
